imager/Imager.py
imager/ImagerData.py
imager/ImagerEncode.py
imager/ImagerFormat.py
imager/__init__.py
imager_client-1.0.0.dist-info/LICENSE
imager_client-1.0.0.dist-info/METADATA
imager_client-1.0.0.dist-info/WHEEL
imager_client-1.0.0.dist-info/entry_points.txt
imager_client-1.0.0.dist-info/top_level.txt
imager_client-1.0.0.dist-info/RECORD
