Metadata-Version: 2.1
Name: imager-client
Version: 1.0.0
Summary: Генерация ссылок на миниатюры картинки в микро-сервисе Imager
Author: Altuhov Vladislav
License: GNU GENERAL PUBLIC LICENSE
Project-URL: Homepage, https://github.com/pkg-ru/imager
Project-URL: Repository, https://github.com/pkg-ru/imager-client
Keywords: assets,imager,image,webp,avif,heif,heic,jpg,png,gif
Classifier: Programming Language :: Python :: 3
Classifier: License :: OSI Approved :: GNU General Public License v3 (GPLv3)
Classifier: Operating System :: OS Independent
Requires-Python: >=3.10.0
License-File: LICENSE
